anzar/__init__.py
anzar/_api/authenticator.py
anzar/_api/client.py
anzar/_api/http_interceptor.py
anzar/_api/jwt_interceptor.py
anzar/_api/session_interceptor.py
anzar/_models/anzar_config.py
anzar/_models/auth.py
anzar/_models/session.py
anzar/_models/user.py
anzar/_utils/context.py
anzar/_utils/errors.py
anzar/_utils/storage.py
anzar/_utils/types.py
anzar/_utils/validator.py
anzar/core/config.py
anzar/core/logger.py
anzar/py.typed
anzar/types.py
anzar-0.2.17.dist-info/WHEEL
anzar-0.2.17.dist-info/METADATA
anzar-0.2.17.dist-info/RECORD
