Metadata-Version: 2.3
Name: anzar
Version: 0.2.17
Summary: Add your description here
Author: Hakou Guelfen
Author-email: Hakou Guelfen <hakoudev@gmail.com>
Requires-Dist: dotenv>=0.9.9
Requires-Dist: keyring>=25.6.0
Requires-Dist: pydantic[email]>=2.11.7
Requires-Dist: pyyaml>=6.0.2
Requires-Dist: requests>=2.32.5
Requires-Python: >=3.14
